retval.py
retval-1.0.2.dist-info/LICENSE
retval-1.0.2.dist-info/METADATA
retval-1.0.2.dist-info/WHEEL
retval-1.0.2.dist-info/top_level.txt
retval-1.0.2.dist-info/RECORD
