Metadata-Version: 2.1
Name: retval
Version: 1.0.2
Summary: a module for easy error-handling without exceptions
Home-page: https://github.com/darkwyrm/retval
Author: Jon Yoder
Author-email: jon@yoder.cloud
License: MIT
Project-URL: Bug Tracker, https://github.com/darkwyrm/retval/issues
Platform: UNKNOWN
Classifier: Development Status :: 5 - Production/Stable
Classifier: Intended Audience :: Developers
Classifier: Topic :: Software Development
Classifier: Programming Language :: Python
Classifier: License :: OSI Approved :: MIT License
Classifier: Operating System :: OS Independent
License-File: LICENSE
